tdir/__init__.py
tdir/py.typed
tdir-1.8.2.dist-info/LICENSE
tdir-1.8.2.dist-info/METADATA
tdir-1.8.2.dist-info/WHEEL
tdir-1.8.2.dist-info/RECORD
