Metadata-Version: 2.1
Name: tdir
Version: 1.8.2
Summary: 🗃 Create and fill a temporary directory 🗃
Home-page: https://github.com/rec/tdir
License: MIT
Author: Tom Ritchford
Author-email: tom@swirly.com
Requires-Python: >=3.8
Classifier: License :: OSI Approved :: MIT License
Classifier: Programming Language :: Python :: 3
Classifier: Programming Language :: Python :: 3.8
Classifier: Programming Language :: Python :: 3.9
Classifier: Programming Language :: Python :: 3.10
Classifier: Programming Language :: Python :: 3.11
Classifier: Programming Language :: Python :: 3.12
Requires-Dist: dek
Requires-Dist: xmod
Project-URL: Documentation, https://rec.github.io/tdir
Project-URL: Repository, https://github.com/rec/tdir
